sqlmodel3/__init__.py
sqlmodel3/_compat.py
sqlmodel3/default.py
sqlmodel3/ext/__init__.py
sqlmodel3/ext/asyncio/__init__.py
sqlmodel3/ext/asyncio/session.py
sqlmodel3/main.py
sqlmodel3/orm/__init__.py
sqlmodel3/orm/session.py
sqlmodel3/pool/__init__.py
sqlmodel3/sql/__init__.py
sqlmodel3/sql/_expression_select_cls.py
sqlmodel3/sql/_expression_select_gen.py
sqlmodel3/sql/_expression_select_gen.py.jinja2
sqlmodel3/sql/base.py
sqlmodel3/sql/expression.py
sqlmodel3/sql/sqltypes.py
sqlmodel3-0.1.0.dist-info/LICENSE
sqlmodel3-0.1.0.dist-info/METADATA
sqlmodel3-0.1.0.dist-info/WHEEL
sqlmodel3-0.1.0.dist-info/RECORD
