Metadata-Version: 2.1
Name: sqlmodel3
Version: 0.1.0
Summary: 
Author: zhangdapeng
Author-email: 1156956636@qq.com
Requires-Python: >=3.12,<4.0
Classifier: Programming Language :: Python :: 3
Classifier: Programming Language :: Python :: 3.12
Classifier: Programming Language :: Python :: 3.13
Requires-Dist: sqlalchemy3 (>=0.1.0,<0.2.0)
